[
    {
        "Date": "2026-02-12",
        "Temperature_C": 17.69,
        "Confidence_Range": "16.7\u00b0C to 18.7\u00b0C",
        "Humidity_%": 55.05,
        "UV_Index": 0.87,
        "WindSpeed_m/s": 6.45,
        "Rainfall_mm": 0.0,
        "Rain_Probability": 0,
        "Rain_Alert": "No Rain \u2600\ufe0f"
    },
    {
        "Date": "2026-02-13",
        "Temperature_C": 17.88,
        "Confidence_Range": "16.9\u00b0C to 18.9\u00b0C",
        "Humidity_%": 54.27,
        "UV_Index": 0.92,
        "WindSpeed_m/s": 6.21,
        "Rainfall_mm": 0.0,
        "Rain_Probability": 0,
        "Rain_Alert": "No Rain \u2600\ufe0f"
    },
    {
        "Date": "2026-02-14",
        "Temperature_C": 18.17,
        "Confidence_Range": "17.2\u00b0C to 19.2\u00b0C",
        "Humidity_%": 53.41,
        "UV_Index": 0.96,
        "WindSpeed_m/s": 6.21,
        "Rainfall_mm": 0.0,
        "Rain_Probability": 0,
        "Rain_Alert": "No Rain \u2600\ufe0f"
    },
    {
        "Date": "2026-02-15",
        "Temperature_C": 18.35,
        "Confidence_Range": "17.3\u00b0C to 19.4\u00b0C",
        "Humidity_%": 53.3,
        "UV_Index": 0.97,
        "WindSpeed_m/s": 6.42,
        "Rainfall_mm": 0.0,
        "Rain_Probability": 0,
        "Rain_Alert": "No Rain \u2600\ufe0f"
    },
    {
        "Date": "2026-02-16",
        "Temperature_C": 18.38,
        "Confidence_Range": "17.4\u00b0C to 19.4\u00b0C",
        "Humidity_%": 52.97,
        "UV_Index": 1.0,
        "WindSpeed_m/s": 6.37,
        "Rainfall_mm": 0.0,
        "Rain_Probability": 0,
        "Rain_Alert": "No Rain \u2600\ufe0f"
    },
    {
        "Date": "2026-02-17",
        "Temperature_C": 18.64,
        "Confidence_Range": "17.6\u00b0C to 19.6\u00b0C",
        "Humidity_%": 51.91,
        "UV_Index": 1.04,
        "WindSpeed_m/s": 6.36,
        "Rainfall_mm": 0.0,
        "Rain_Probability": 0,
        "Rain_Alert": "No Rain \u2600\ufe0f"
    },
    {
        "Date": "2026-02-18",
        "Temperature_C": 18.69,
        "Confidence_Range": "17.7\u00b0C to 19.7\u00b0C",
        "Humidity_%": 52.06,
        "UV_Index": 1.02,
        "WindSpeed_m/s": 6.3,
        "Rainfall_mm": 0.09,
        "Rain_Probability": 1.3,
        "Rain_Alert": "No Rain \u2600\ufe0f"
    }
]